{
  "generatedAt": "2026-03-07T15:15:16.036Z",
  "county": {
    "id": "高雄市",
    "name": "高雄市",
    "shortLabel": "高雄",
    "region": "南部"
  },
  "precisions": {
    "5": [
      {
        "id": "5-wsj8f",
        "geohash": "wsj8f",
        "precision": 5,
        "count": 1,
        "latitude": 22.651163,
        "longitude": 120.328524,
        "bounds": {
          "minLatitude": 22.651163,
          "maxLatitude": 22.651163,
          "minLongitude": 120.328524,
          "maxLongitude": 120.328524
        },
        "topSchools": [
          {
            "id": "0053",
            "name": "國立高雄科技大學",
            "townshipName": "三民區",
            "students": 27394,
            "status": "正常"
          }
        ]
      },
      {
        "id": "5-wsj87",
        "geohash": "wsj87",
        "precision": 5,
        "count": 1,
        "latitude": 22.564587,
        "longitude": 120.371956,
        "bounds": {
          "minLatitude": 22.564587,
          "maxLatitude": 22.564587,
          "minLongitude": 120.371956,
          "maxLongitude": 120.371956
        },
        "topSchools": [
          {
            "id": "0047",
            "name": "國立高雄餐旅大學",
            "townshipName": "小港區",
            "students": 4101,
            "status": "正常"
          }
        ]
      },
      {
        "id": "5-wsj89",
        "geohash": "wsj89",
        "precision": 5,
        "count": 1,
        "latitude": 22.625518,
        "longitude": 120.320032,
        "bounds": {
          "minLatitude": 22.625518,
          "maxLatitude": 22.625518,
          "minLongitude": 120.320032,
          "maxLongitude": 120.320032
        },
        "topSchools": [
          {
            "id": "0014",
            "name": "國立高雄師範大學",
            "townshipName": "苓雅區",
            "students": 7262,
            "status": "正常"
          }
        ]
      },
      {
        "id": "5-wsj93",
        "geohash": "wsj93",
        "precision": 5,
        "count": 1,
        "latitude": 22.734378,
        "longitude": 120.285089,
        "bounds": {
          "minLatitude": 22.734378,
          "maxLatitude": 22.734378,
          "minLongitude": 120.285089,
          "maxLongitude": 120.285089
        },
        "topSchools": [
          {
            "id": "0019",
            "name": "國立高雄大學",
            "townshipName": "楠梓區",
            "students": 6192,
            "status": "正常"
          }
        ]
      },
      {
        "id": "5-wsj88",
        "geohash": "wsj88",
        "precision": 5,
        "count": 1,
        "latitude": 22.625793,
        "longitude": 120.265808,
        "bounds": {
          "minLatitude": 22.625793,
          "maxLatitude": 22.625793,
          "minLongitude": 120.265808,
          "maxLongitude": 120.265808
        },
        "topSchools": [
          {
            "id": "0009",
            "name": "國立中山大學",
            "townshipName": "鼓山區",
            "students": 10948,
            "status": "正常"
          }
        ]
      }
    ],
    "6": [
      {
        "id": "6-wsj8f5",
        "geohash": "wsj8f5",
        "precision": 6,
        "count": 1,
        "latitude": 22.651163,
        "longitude": 120.328524,
        "bounds": {
          "minLatitude": 22.651163,
          "maxLatitude": 22.651163,
          "minLongitude": 120.328524,
          "maxLongitude": 120.328524
        },
        "topSchools": [
          {
            "id": "0053",
            "name": "國立高雄科技大學",
            "townshipName": "三民區",
            "students": 27394,
            "status": "正常"
          }
        ]
      },
      {
        "id": "6-wsj875",
        "geohash": "wsj875",
        "precision": 6,
        "count": 1,
        "latitude": 22.564587,
        "longitude": 120.371956,
        "bounds": {
          "minLatitude": 22.564587,
          "maxLatitude": 22.564587,
          "minLongitude": 120.371956,
          "maxLongitude": 120.371956
        },
        "topSchools": [
          {
            "id": "0047",
            "name": "國立高雄餐旅大學",
            "townshipName": "小港區",
            "students": 4101,
            "status": "正常"
          }
        ]
      },
      {
        "id": "6-wsj89y",
        "geohash": "wsj89y",
        "precision": 6,
        "count": 1,
        "latitude": 22.625518,
        "longitude": 120.320032,
        "bounds": {
          "minLatitude": 22.625518,
          "maxLatitude": 22.625518,
          "minLongitude": 120.320032,
          "maxLongitude": 120.320032
        },
        "topSchools": [
          {
            "id": "0014",
            "name": "國立高雄師範大學",
            "townshipName": "苓雅區",
            "students": 7262,
            "status": "正常"
          }
        ]
      },
      {
        "id": "6-wsj934",
        "geohash": "wsj934",
        "precision": 6,
        "count": 1,
        "latitude": 22.734378,
        "longitude": 120.285089,
        "bounds": {
          "minLatitude": 22.734378,
          "maxLatitude": 22.734378,
          "minLongitude": 120.285089,
          "maxLongitude": 120.285089
        },
        "topSchools": [
          {
            "id": "0019",
            "name": "國立高雄大學",
            "townshipName": "楠梓區",
            "students": 6192,
            "status": "正常"
          }
        ]
      },
      {
        "id": "6-wsj88w",
        "geohash": "wsj88w",
        "precision": 6,
        "count": 1,
        "latitude": 22.625793,
        "longitude": 120.265808,
        "bounds": {
          "minLatitude": 22.625793,
          "maxLatitude": 22.625793,
          "minLongitude": 120.265808,
          "maxLongitude": 120.265808
        },
        "topSchools": [
          {
            "id": "0009",
            "name": "國立中山大學",
            "townshipName": "鼓山區",
            "students": 10948,
            "status": "正常"
          }
        ]
      }
    ],
    "7": [
      {
        "id": "7-wsj8f5s",
        "geohash": "wsj8f5s",
        "precision": 7,
        "count": 1,
        "latitude": 22.651163,
        "longitude": 120.328524,
        "bounds": {
          "minLatitude": 22.651163,
          "maxLatitude": 22.651163,
          "minLongitude": 120.328524,
          "maxLongitude": 120.328524
        },
        "topSchools": [
          {
            "id": "0053",
            "name": "國立高雄科技大學",
            "townshipName": "三民區",
            "students": 27394,
            "status": "正常"
          }
        ]
      },
      {
        "id": "7-wsj875u",
        "geohash": "wsj875u",
        "precision": 7,
        "count": 1,
        "latitude": 22.564587,
        "longitude": 120.371956,
        "bounds": {
          "minLatitude": 22.564587,
          "maxLatitude": 22.564587,
          "minLongitude": 120.371956,
          "maxLongitude": 120.371956
        },
        "topSchools": [
          {
            "id": "0047",
            "name": "國立高雄餐旅大學",
            "townshipName": "小港區",
            "students": 4101,
            "status": "正常"
          }
        ]
      },
      {
        "id": "7-wsj89yy",
        "geohash": "wsj89yy",
        "precision": 7,
        "count": 1,
        "latitude": 22.625518,
        "longitude": 120.320032,
        "bounds": {
          "minLatitude": 22.625518,
          "maxLatitude": 22.625518,
          "minLongitude": 120.320032,
          "maxLongitude": 120.320032
        },
        "topSchools": [
          {
            "id": "0014",
            "name": "國立高雄師範大學",
            "townshipName": "苓雅區",
            "students": 7262,
            "status": "正常"
          }
        ]
      },
      {
        "id": "7-wsj934s",
        "geohash": "wsj934s",
        "precision": 7,
        "count": 1,
        "latitude": 22.734378,
        "longitude": 120.285089,
        "bounds": {
          "minLatitude": 22.734378,
          "maxLatitude": 22.734378,
          "minLongitude": 120.285089,
          "maxLongitude": 120.285089
        },
        "topSchools": [
          {
            "id": "0019",
            "name": "國立高雄大學",
            "townshipName": "楠梓區",
            "students": 6192,
            "status": "正常"
          }
        ]
      },
      {
        "id": "7-wsj88wy",
        "geohash": "wsj88wy",
        "precision": 7,
        "count": 1,
        "latitude": 22.625793,
        "longitude": 120.265808,
        "bounds": {
          "minLatitude": 22.625793,
          "maxLatitude": 22.625793,
          "minLongitude": 120.265808,
          "maxLongitude": 120.265808
        },
        "topSchools": [
          {
            "id": "0009",
            "name": "國立中山大學",
            "townshipName": "鼓山區",
            "students": 10948,
            "status": "正常"
          }
        ]
      }
    ]
  }
}
